CHANGES.rst
CREDITS.rst
LICENSE.rst
MANIFEST.in
README.rst
TODO.rst
setup.cfg
setup.py
turn/__init__.py
turn/console.py
turn/core.py
turn/tests.py
turn/tools.py
turn.egg-info/PKG-INFO
turn.egg-info/SOURCES.txt
turn.egg-info/dependency_links.txt
turn.egg-info/entry_points.txt
turn.egg-info/not-zip-safe
turn.egg-info/requires.txt
turn.egg-info/top_level.txt