Metadata-Version: 1.0
Name: turn
Version: 0.3
Summary: A shared-resource-locking queue system using python and redis.
Home-page: UNKNOWN
Author: Arjan Verkerk
Author-email: arjan.verkerk@nelen-schuurmans.nl
License: GPL
Platform: UNKNOWN
